unittest2/signals.py
unittest2/result.py
unittest2/main.py
unittest2/__init__.py
unittest2/loader.py
unittest2/runner.py
unittest2/compatibility.py
unittest2/__main__.py
unittest2/suite.py
unittest2/collector.py
unittest2/util.py
unittest2/case.py
unittest2/test/test_suite.py
unittest2/test/_test_unittest2_with.py
unittest2/test/dummy.py
unittest2/test/test_skipping.py
unittest2/test/__init__.py
unittest2/test/test_break.py
unittest2/test/test_runner.py
unittest2/test/test_case.py
unittest2/test/test_new_tests.py
unittest2/test/test_loader.py
unittest2/test/test_unittest2_with.py
unittest2/test/test_assertions.py
unittest2/test/test_result.py
unittest2/test/test_functiontestcase.py
unittest2/test/test_discovery.py
unittest2/test/test_program.py
unittest2/test/test_setups.py
unittest2/test/support.py
unittest2-1.0.0.dist-info/entry_points.txt
unittest2-1.0.0.dist-info/metadata.json
unittest2-1.0.0.dist-info/DESCRIPTION.rst
unittest2-1.0.0.dist-info/RECORD
unittest2-1.0.0.dist-info/top_level.txt
unittest2-1.0.0.dist-info/WHEEL
unittest2-1.0.0.dist-info/METADATA
