Metadata-Version: 2.0
Name: unittest2
Version: 1.0.0
Summary: The new features in unittest backported to Python 2.4+.
Home-page: http://pypi.python.org/pypi/unittest2
Author: Michael Foord
Author-email: michael@voidspace.org.uk
License: UNKNOWN
Keywords: unittest,testing,tests
Platform: UNKNOWN
Classifier: Development Status :: 4 - Beta
Classifier: Environment :: Console
Classifier: Intended Audience :: Developers
Classifier: License :: OSI Approved :: BSD License
Classifier: Programming Language :: Python
Classifier: Programming Language :: Python :: 2.4
Classifier: Programming Language :: Python :: 2.5
Classifier: Programming Language :: Python :: 2.6
Classifier: Programming Language :: Python :: 2.7
Classifier: Operating System :: OS Independent
Classifier: Topic :: Software Development :: Libraries
Classifier: Topic :: Software Development :: Libraries :: Python Modules
Classifier: Topic :: Software Development :: Testing
Requires-Dist: argparse
Requires-Dist: six
Requires-Dist: traceback2
